declinate/__init__.py
declinate/__main__.py
declinate/check.py
declinate/cli.py
declinate/declinate.py
declinate/gen.py
declinate/py.typed
declinate-0.0.6.dist-info/licenses/LICENSE.txt
declinate-0.0.6.dist-info/METADATA
declinate-0.0.6.dist-info/WHEEL
declinate-0.0.6.dist-info/entry_points.txt
declinate-0.0.6.dist-info/top_level.txt
declinate-0.0.6.dist-info/RECORD
