Metadata-Version: 2.4
Name: declinate
Version: 0.0.6
Summary: CLI generator.
Author-email: Ternaris <team@ternaris.com>
License-Expression: Apache-2.0
Project-URL: Homepage, https://gitlab.com/ternaris/declinate
Project-URL: Documentation, https://ternaris.gitlab.io/declinate
Project-URL: Source, https://gitlab.com/ternaris/declinate
Project-URL: Issues, https://gitlab.com/ternaris/declinate/issues
Project-URL: Changelog, https://gitlab.com/ternaris/declinate/-/blob/master/CHANGES.rst
Keywords: cli
Classifier: Development Status :: 3 - Alpha
Classifier: Intended Audience :: Developers
Classifier: Operating System :: OS Independent
Classifier: Programming Language :: Python
Classifier: Programming Language :: Python :: 3 :: Only
Classifier: Programming Language :: Python :: 3.10
Classifier: Programming Language :: Python :: 3.11
Classifier: Programming Language :: Python :: 3.12
Classifier: Programming Language :: Python :: 3.13
Classifier: Typing :: Typed
Requires-Python: >=3.10
License-File: LICENSE.txt
Requires-Dist: typing_extensions
Dynamic: license-file
